rv3028/__init__.py
rv3028-0.0.5.dist-info/LICENSE.txt
rv3028-0.0.5.dist-info/METADATA
rv3028-0.0.5.dist-info/WHEEL
rv3028-0.0.5.dist-info/top_level.txt
rv3028-0.0.5.dist-info/RECORD
