Metadata-Version: 2.1
Name: rv3028
Version: 0.0.5
Summary: Python library for the RV3028 Real Time Clock 
Home-page: http://www.pimoroni.com
Author: Gee Bartlett
Author-email: gee@pimoroni.com
License: MIT
Project-URL: GitHub, https://www.github.com/pimoroni/rv3028-python
Keywords: Raspberry Pi
Platform: UNKNOWN
Classifier: Development Status :: 4 - Beta
Classifier: Operating System :: POSIX :: Linux
Classifier: License :: OSI Approved :: MIT License
Classifier: Intended Audience :: Developers
Classifier: Programming Language :: Python :: 2.6
Classifier: Programming Language :: Python :: 2.7
Classifier: Programming Language :: Python :: 3
Classifier: Topic :: Software Development
Classifier: Topic :: System :: Hardware
Requires-Dist: i2cdevice (>=0.0.6)
